<?xml version="1.0" encoding="UTF-8"?>
<databaseChangeLog
        xmlns="http://www.liquibase.org/xml/ns/dbchangelog"
        xmlns:xsi="http://www.w3.org/2001/XMLSchema-instance"
        xsi:schemaLocation="http://www.liquibase.org/xml/ns/dbchangelog
        http://www.liquibase.org/xml/ns/dbchangelog/dbchangelog-4.20.xsd">

    <changeSet id="004-seed-data" author="aiylbank" context="dev">
        <insert tableName="accounts">
            <column name="account_number" value="KG001000000001"/>
            <column name="owner_name"     value="Aibek Dzhaksybekov"/>
            <column name="balance"        valueNumeric="50000.00"/>
            <column name="status"         value="ACTIVE"/>
        </insert>
        <insert tableName="accounts">
            <column name="account_number" value="KG001000000002"/>
            <column name="owner_name"     value="Ainur Mamytbekova"/>
            <column name="balance"        valueNumeric="15000.00"/>
            <column name="status"         value="ACTIVE"/>
        </insert>
        <insert tableName="accounts">
            <column name="account_number" value="KG001000000003"/>
            <column name="owner_name"     value="Bakyt Osmonov"/>
            <column name="balance"        valueNumeric="2000.00"/>
            <column name="status"         value="ACTIVE"/>
        </insert>
        <insert tableName="accounts">
            <column name="account_number" value="KG001000000004"/>
            <column name="owner_name"     value="Gulnara Toktobekova"/>
            <column name="balance"        valueNumeric="0.00"/>
            <column name="status"         value="BLOCKED"/>
        </insert>
        <insert tableName="accounts">
            <column name="account_number" value="KG001000000005"/>
            <column name="owner_name"     value="Daniyar Sydykov"/>
            <column name="balance"        valueNumeric="99999.99"/>
            <column name="status"         value="ACTIVE"/>
        </insert>

        <rollback>
            <delete tableName="accounts">
                <where>account_number IN ('KG001000000001','KG001000000002','KG001000000003','KG001000000004','KG001000000005')</where>
            </delete>
        </rollback>
    </changeSet>

</databaseChangeLog>